pytimeconv/__init__.py
pytimeconv/_timeconv.py
pytimeconv/py.typed
pytimeconv-0.0.2.dist-info/LICENSE
pytimeconv-0.0.2.dist-info/METADATA
pytimeconv-0.0.2.dist-info/WHEEL
pytimeconv-0.0.2.dist-info/top_level.txt
pytimeconv-0.0.2.dist-info/RECORD
